waterwheel/__init__.py
waterwheel/waterwheel.py
waterwheel/resources/doc_bins.msgpack
waterwheel-0.4.0.dist-info/LICENSE
waterwheel-0.4.0.dist-info/METADATA
waterwheel-0.4.0.dist-info/WHEEL
waterwheel-0.4.0.dist-info/top_level.txt
waterwheel-0.4.0.dist-info/RECORD
