Metadata-Version: 2.1
Name: waterwheel
Version: 0.4.0
Summary: Spacy Pipeline Component for Hydrologic Entity Extraction
Home-page: https://github.com/gwf-uwaterloo/waterwheel
Author: Govind Sharma
Author-email: govind.sharma@uwaterloo.ca
License: UNKNOWN
Platform: UNKNOWN
Classifier: Programming Language :: Python :: 3
Classifier: License :: OSI Approved :: Apache Software License
Classifier: Operating System :: OS Independent
Requires-Python: >=3.6
Requires-Dist: spacy (==2.2.3)
